doc/conf.py
nxtomo/__init__.py
nxtomo/io.py
nxtomo/version.py
nxtomo/application/nxtomo.py
nxtomo/application/tests/test_nxtomo.py
nxtomo/geometry/_CoordinateSystem.py
nxtomo/geometry/__init__.py
nxtomo/nxobject/__init__.py
nxtomo/nxobject/nxdetector.py
nxtomo/nxobject/nxinstrument.py
nxtomo/nxobject/nxmonitor.py
nxtomo/nxobject/nxobject.py
nxtomo/nxobject/nxsample.py
nxtomo/nxobject/nxsource.py
nxtomo/nxobject/nxtransformations.py
nxtomo/nxobject/tests/test_nxdetector.py
nxtomo/nxobject/tests/test_nxinstrument.py
nxtomo/nxobject/tests/test_nxmonitor.py
nxtomo/nxobject/tests/test_nxobject.py
nxtomo/nxobject/tests/test_nxsample.py
nxtomo/nxobject/tests/test_nxsource.py
nxtomo/nxobject/tests/test_nxtransformations.py
nxtomo/nxobject/utils/ObjectWithPixelSizeMixIn.py
nxtomo/nxobject/utils/__init__.py
nxtomo/nxobject/utils/concatenate.py
nxtomo/nxobject/utils/decorator.py
nxtomo/paths/__init__.py
nxtomo/paths/nxdetector.py
nxtomo/paths/nxinstrument.py
nxtomo/paths/nxmonitor.py
nxtomo/paths/nxsample.py
nxtomo/paths/nxsource.py
nxtomo/paths/nxtomo.py
nxtomo/paths/nxtransformations.py
nxtomo/paths/tests/test_backward_compatibility.py
nxtomo/utils/NXtomoSplitter.py
nxtomo/utils/__init__.py
nxtomo/utils/detectorsplitter.py
nxtomo/utils/frameappender.py
nxtomo/utils/io.py
nxtomo/utils/transformation.py
nxtomo/utils/utils.py
nxtomo/utils/tests/test_splitter.py
nxtomo/utils/tests/test_transformation.py
nxtomo-3.0.3.dist-info/licenses/LICENSE
nxtomo-3.0.3.dist-info/METADATA
nxtomo-3.0.3.dist-info/WHEEL
nxtomo-3.0.3.dist-info/top_level.txt
nxtomo-3.0.3.dist-info/RECORD
